LICENCE
README.md
pyproject.toml
setup.py
dynamic_network_architectures/__init__.py
dynamic_network_architectures.egg-info/PKG-INFO
dynamic_network_architectures.egg-info/SOURCES.txt
dynamic_network_architectures.egg-info/dependency_links.txt
dynamic_network_architectures.egg-info/not-zip-safe
dynamic_network_architectures.egg-info/requires.txt
dynamic_network_architectures.egg-info/top_level.txt
dynamic_network_architectures/architectures/__init__.py
dynamic_network_architectures/architectures/abstract_arch.py
dynamic_network_architectures/architectures/primus.py
dynamic_network_architectures/architectures/resnet.py
dynamic_network_architectures/architectures/unet.py
dynamic_network_architectures/architectures/vgg.py
dynamic_network_architectures/building_blocks/__init__.py
dynamic_network_architectures/building_blocks/eva.py
dynamic_network_architectures/building_blocks/helper.py
dynamic_network_architectures/building_blocks/patch_encode_decode.py
dynamic_network_architectures/building_blocks/plain_conv_encoder.py
dynamic_network_architectures/building_blocks/regularization.py
dynamic_network_architectures/building_blocks/residual.py
dynamic_network_architectures/building_blocks/residual_encoders.py
dynamic_network_architectures/building_blocks/simple_conv_blocks.py
dynamic_network_architectures/building_blocks/unet_decoder.py
dynamic_network_architectures/building_blocks/unet_residual_decoder.py
dynamic_network_architectures/initialization/__init__.py
dynamic_network_architectures/initialization/weight_init.py