Metadata-Version: 2.1
Name: dynamic_network_architectures
Version: 0.4.3
Summary: none
Author-email: Fabian Isensee <f.isensee@dkfz.de>
Requires-Python: >=3.8
License-File: LICENCE
Requires-Dist: torch>=1.6.0a
Requires-Dist: numpy
Requires-Dist: timm<1.0.23
Requires-Dist: einops
